sortrenamer/gui.py
sortrenamer/languages.py
sortrenamer/toolbox.py
sortrenamer-1.0.0.dist-info/LICENSE
sortrenamer-1.0.0.dist-info/METADATA
sortrenamer-1.0.0.dist-info/WHEEL
sortrenamer-1.0.0.dist-info/entry_points.txt
sortrenamer-1.0.0.dist-info/top_level.txt
sortrenamer-1.0.0.dist-info/RECORD
