Metadata-Version: 2.1
Name: sortrenamer
Version: 1.0.0
Summary: Cross-platform desktop GUI app, that renames/moves (sorts) images and other files, and finds and moves duplicates.
Author-email: DrSugak <dr.sugak.dev@gmail.com>
Project-URL: Homepage, https://github.com/DrSugak/sortrenamer
Keywords: exif,rename,move,duplicates
Classifier: Programming Language :: Python :: 3
Classifier: License :: OSI Approved :: GNU General Public License v3 (GPLv3)
Classifier: Operating System :: OS Independent
Requires-Python: >=3.12
License-File: LICENSE
Requires-Dist: PyQt6
Requires-Dist: pillow
